yiban/__init__.py
yiban/__main__.py
yiban/base.py
yiban/data.py
yiban/edata.py
yiban/mp.py
yiban/openapi.py
yiban-0.7.0.1.dist-info/LICENSE
yiban-0.7.0.1.dist-info/METADATA
yiban-0.7.0.1.dist-info/WHEEL
yiban-0.7.0.1.dist-info/top_level.txt
yiban-0.7.0.1.dist-info/RECORD
